cc_plugin_ugrid/__init__.py
cc_plugin_ugrid/_version.py
cc_plugin_ugrid/checker.py
cc_plugin_ugrid/tests/test_checker.py
cc_plugin_ugrid-1.1.0.dist-info/licenses/LICENSE.txt
cc_plugin_ugrid-1.1.0.dist-info/METADATA
cc_plugin_ugrid-1.1.0.dist-info/WHEEL
cc_plugin_ugrid-1.1.0.dist-info/entry_points.txt
cc_plugin_ugrid-1.1.0.dist-info/top_level.txt
cc_plugin_ugrid-1.1.0.dist-info/RECORD
