Metadata-Version: 2.4
Name: cc-plugin-ugrid
Version: 1.1.0
Summary: UGRID plugin for the IOOS Compliance Checker Plugin
Maintainer: Filipe Fernandes
Maintainer-email: Brian McKenna <brian.mckenna@rpsgroup.com>
License: Apache-2.0
Project-URL: documentation, http://ioos.github.io/compliance-checker/
Project-URL: homepage, https://github.com/ioos/cc-plugin-ugrid
Project-URL: repository, https://github.com/ioos/cc-plugin-ugrid
Classifier: Programming Language :: Python :: 3 :: Only
Classifier: Programming Language :: Python :: 3.9
Classifier: Programming Language :: Python :: 3.10
Classifier: Programming Language :: Python :: 3.11
Classifier: Programming Language :: Python :: 3.12
Classifier: Programming Language :: Python :: 3.13
Requires-Python: >=3.9
License-File: LICENSE.txt
Requires-Dist: compliance-checker>=4.0.0
Requires-Dist: netCDF4>=1.4.0
Dynamic: license-file
